count_min_sketch_rs-1.0.0.dist-info/METADATA
count_min_sketch_rs-1.0.0.dist-info/WHEEL
count_min_sketch/__init__.py
count_min_sketch/count_min_sketch.cpython-39-darwin.so
count_min_sketch_rs-1.0.0.dist-info/RECORD
