Metadata-Version: 2.1
Name: count-min-sketch-rs
Version: 1.0.0
Summary: A fast CMS streaming data structure implemented in rust
Author: m-m-adams <52469396+m-m-adams@users.noreply.github.com>
Author-email: m-m-adams <52469396+m-m-adams@users.noreply.github.com>
Project-URL: Source Code, https://github.com/m-m-adams/count_min_sketch
